{
  "experiment_name": "cifar10_krum_c50_m15",
  "timestamp": "20251203_020435",
  "rounds": [
    {
      "round": 0,
      "loss": 2.3031299655048993,
      "accuracy": 0.101
    },
    {
      "round": 1,
      "loss": 2.3011387529464575,
      "accuracy": 0.1022
    },
    {
      "round": 2,
      "loss": 2.299218563226084,
      "accuracy": 0.136
    },
    {
      "round": 3,
      "loss": 2.2963655916646646,
      "accuracy": 0.1848
    },
    {
      "round": 4,
      "loss": 2.2911623034614346,
      "accuracy": 0.2116
    },
    {
      "round": 5,
      "loss": 2.2797063516732603,
      "accuracy": 0.2424
    },
    {
      "round": 6,
      "loss": 2.246930486477983,
      "accuracy": 0.2231
    },
    {
      "round": 7,
      "loss": 2.166636084596189,
      "accuracy": 0.2229
    },
    {
      "round": 8,
      "loss": 2.0897218499320767,
      "accuracy": 0.2472
    },
    {
      "round": 9,
      "loss": 2.036524637819479,
      "accuracy": 0.2571
    },
    {
      "round": 10,
      "loss": 2.0017183070746474,
      "accuracy": 0.2649
    },
    {
      "round": 11,
      "loss": 1.9756019336347002,
      "accuracy": 0.2738
    },
    {
      "round": 12,
      "loss": 1.954296171093901,
      "accuracy": 0.2897
    },
    {
      "round": 13,
      "loss": 1.920212070020243,
      "accuracy": 0.2972
    },
    {
      "round": 14,
      "loss": 1.8943058134267887,
      "accuracy": 0.3114
    },
    {
      "round": 15,
      "loss": 1.8688146618608468,
      "accuracy": 0.3241
    },
    {
      "round": 16,
      "loss": 1.8282909663721396,
      "accuracy": 0.3333
    },
    {
      "round": 17,
      "loss": 1.7936754196215743,
      "accuracy": 0.3599
    },
    {
      "round": 18,
      "loss": 1.7556120378140825,
      "accuracy": 0.3599
    },
    {
      "round": 19,
      "loss": 1.7318353268285147,
      "accuracy": 0.3741
    },
    {
      "round": 20,
      "loss": 1.694823201472005,
      "accuracy": 0.3904
    },
    {
      "round": 21,
      "loss": 1.6773497159488666,
      "accuracy": 0.3939
    },
    {
      "round": 22,
      "loss": 1.6542634004221175,
      "accuracy": 0.4042
    },
    {
      "round": 23,
      "loss": 1.6419500638120852,
      "accuracy": 0.4104
    },
    {
      "round": 24,
      "loss": 1.6095435032829308,
      "accuracy": 0.4181
    },
    {
      "round": 25,
      "loss": 1.592813738618796,
      "accuracy": 0.425
    },
    {
      "round": 26,
      "loss": 1.583856901040854,
      "accuracy": 0.4264
    },
    {
      "round": 27,
      "loss": 1.5693944075617927,
      "accuracy": 0.4352
    },
    {
      "round": 28,
      "loss": 1.5450716986062047,
      "accuracy": 0.4395
    },
    {
      "round": 29,
      "loss": 1.5275240774733572,
      "accuracy": 0.4479
    },
    {
      "round": 30,
      "loss": 1.5233795543829092,
      "accuracy": 0.4531
    },
    {
      "round": 31,
      "loss": 1.4983265540851192,
      "accuracy": 0.4558
    },
    {
      "round": 32,
      "loss": 1.4834322293345539,
      "accuracy": 0.464
    },
    {
      "round": 33,
      "loss": 1.4768573460868373,
      "accuracy": 0.4667
    },
    {
      "round": 34,
      "loss": 1.458026973965069,
      "accuracy": 0.4748
    },
    {
      "round": 35,
      "loss": 1.4527078710805874,
      "accuracy": 0.4788
    },
    {
      "round": 36,
      "loss": 1.4335924227016803,
      "accuracy": 0.4836
    },
    {
      "round": 37,
      "loss": 1.4203851939009402,
      "accuracy": 0.4878
    },
    {
      "round": 38,
      "loss": 1.3997003799810197,
      "accuracy": 0.4957
    },
    {
      "round": 39,
      "loss": 1.3998850054634264,
      "accuracy": 0.499
    },
    {
      "round": 40,
      "loss": 1.3841286158790223,
      "accuracy": 0.5021
    },
    {
      "round": 41,
      "loss": 1.369869337295191,
      "accuracy": 0.5063
    },
    {
      "round": 42,
      "loss": 1.361418887830009,
      "accuracy": 0.5123
    },
    {
      "round": 43,
      "loss": 1.3473745005580182,
      "accuracy": 0.5164
    },
    {
      "round": 44,
      "loss": 1.3421018142669727,
      "accuracy": 0.5208
    },
    {
      "round": 45,
      "loss": 1.3284570313871098,
      "accuracy": 0.5279
    },
    {
      "round": 46,
      "loss": 1.3191179775963195,
      "accuracy": 0.5268
    },
    {
      "round": 47,
      "loss": 1.3138104574368024,
      "accuracy": 0.5335
    },
    {
      "round": 48,
      "loss": 1.2974213712131635,
      "accuracy": 0.5334
    },
    {
      "round": 49,
      "loss": 1.291929275273515,
      "accuracy": 0.5383
    },
    {
      "round": 50,
      "loss": 1.2835627512429089,
      "accuracy": 0.545
    },
    {
      "round": 51,
      "loss": 1.2744963738484123,
      "accuracy": 0.5492
    },
    {
      "round": 52,
      "loss": 1.2709812965636818,
      "accuracy": 0.551
    },
    {
      "round": 53,
      "loss": 1.2517968652347407,
      "accuracy": 0.555
    },
    {
      "round": 54,
      "loss": 1.244743397441535,
      "accuracy": 0.558
    },
    {
      "round": 55,
      "loss": 1.241978658464389,
      "accuracy": 0.5632
    },
    {
      "round": 56,
      "loss": 1.2351703822803193,
      "accuracy": 0.563
    },
    {
      "round": 57,
      "loss": 1.2262935632714829,
      "accuracy": 0.5655
    },
    {
      "round": 58,
      "loss": 1.2234599100895964,
      "accuracy": 0.5714
    },
    {
      "round": 59,
      "loss": 1.2029368643181773,
      "accuracy": 0.577
    },
    {
      "round": 60,
      "loss": 1.1998042805126299,
      "accuracy": 0.5752
    },
    {
      "round": 61,
      "loss": 1.1889132956346384,
      "accuracy": 0.5792
    },
    {
      "round": 62,
      "loss": 1.1873391091633148,
      "accuracy": 0.588
    },
    {
      "round": 63,
      "loss": 1.1797428013036808,
      "accuracy": 0.5845
    },
    {
      "round": 64,
      "loss": 1.17165034837997,
      "accuracy": 0.592
    },
    {
      "round": 65,
      "loss": 1.1568567501470304,
      "accuracy": 0.5933
    },
    {
      "round": 66,
      "loss": 1.1563633746994189,
      "accuracy": 0.5937
    },
    {
      "round": 67,
      "loss": 1.147940804973578,
      "accuracy": 0.5946
    },
    {
      "round": 68,
      "loss": 1.1321384769659073,
      "accuracy": 0.6017
    },
    {
      "round": 69,
      "loss": 1.1336669982812655,
      "accuracy": 0.6011
    },
    {
      "round": 70,
      "loss": 1.125258764519859,
      "accuracy": 0.6056
    },
    {
      "round": 71,
      "loss": 1.1178635031270523,
      "accuracy": 0.6109
    },
    {
      "round": 72,
      "loss": 1.1142283196266467,
      "accuracy": 0.6072
    },
    {
      "round": 73,
      "loss": 1.1014058827973021,
      "accuracy": 0.6137
    },
    {
      "round": 74,
      "loss": 1.1042813329270091,
      "accuracy": 0.6092
    },
    {
      "round": 75,
      "loss": 1.0880430175092655,
      "accuracy": 0.616
    },
    {
      "round": 76,
      "loss": 1.082398684260944,
      "accuracy": 0.618
    },
    {
      "round": 77,
      "loss": 1.0797134291249724,
      "accuracy": 0.6197
    },
    {
      "round": 78,
      "loss": 1.067530046446255,
      "accuracy": 0.622
    },
    {
      "round": 79,
      "loss": 1.064690872503165,
      "accuracy": 0.6281
    },
    {
      "round": 80,
      "loss": 1.0535579264735262,
      "accuracy": 0.6298
    },
    {
      "round": 81,
      "loss": 1.061909729299454,
      "accuracy": 0.6297
    },
    {
      "round": 82,
      "loss": 1.0425608708454779,
      "accuracy": 0.6341
    },
    {
      "round": 83,
      "loss": 1.0368519779592276,
      "accuracy": 0.6374
    },
    {
      "round": 84,
      "loss": 1.0290463959066252,
      "accuracy": 0.6366
    },
    {
      "round": 85,
      "loss": 1.0204083668157315,
      "accuracy": 0.6441
    },
    {
      "round": 86,
      "loss": 1.0127677271922175,
      "accuracy": 0.6455
    },
    {
      "round": 87,
      "loss": 1.013022925145329,
      "accuracy": 0.6492
    },
    {
      "round": 88,
      "loss": 1.001546770619889,
      "accuracy": 0.6506
    },
    {
      "round": 89,
      "loss": 0.9965693840203574,
      "accuracy": 0.6496
    },
    {
      "round": 90,
      "loss": 0.9930071472740782,
      "accuracy": 0.6531
    },
    {
      "round": 91,
      "loss": 0.9850015670727617,
      "accuracy": 0.656
    },
    {
      "round": 92,
      "loss": 0.9868812530566329,
      "accuracy": 0.661
    },
    {
      "round": 93,
      "loss": 0.9712710411023027,
      "accuracy": 0.6618
    },
    {
      "round": 94,
      "loss": 0.9750638423255458,
      "accuracy": 0.6608
    },
    {
      "round": 95,
      "loss": 0.9667785245770464,
      "accuracy": 0.6615
    },
    {
      "round": 96,
      "loss": 0.9566689329787185,
      "accuracy": 0.6707
    },
    {
      "round": 97,
      "loss": 0.9516623976131597,
      "accuracy": 0.6677
    },
    {
      "round": 98,
      "loss": 0.9511270639233695,
      "accuracy": 0.6688
    },
    {
      "round": 99,
      "loss": 0.9443755519275848,
      "accuracy": 0.6736
    },
    {
      "round": 100,
      "loss": 0.9387250320789532,
      "accuracy": 0.6768
    },
    {
      "round": 101,
      "loss": 0.9393338161154677,
      "accuracy": 0.6731
    },
    {
      "round": 102,
      "loss": 0.9331488770227463,
      "accuracy": 0.6769
    },
    {
      "round": 103,
      "loss": 0.9234741359663466,
      "accuracy": 0.6783
    },
    {
      "round": 104,
      "loss": 0.9196136357685247,
      "accuracy": 0.6815
    },
    {
      "round": 105,
      "loss": 0.9172937882403596,
      "accuracy": 0.6818
    },
    {
      "round": 106,
      "loss": 0.9142537549280891,
      "accuracy": 0.6826
    },
    {
      "round": 107,
      "loss": 0.9087625480117127,
      "accuracy": 0.6863
    },
    {
      "round": 108,
      "loss": 0.9077609475618734,
      "accuracy": 0.6834
    },
    {
      "round": 109,
      "loss": 0.9042973918274949,
      "accuracy": 0.6865
    },
    {
      "round": 110,
      "loss": 0.9005721353303892,
      "accuracy": 0.6862
    },
    {
      "round": 111,
      "loss": 0.8923253681713019,
      "accuracy": 0.6908
    },
    {
      "round": 112,
      "loss": 0.888975736336967,
      "accuracy": 0.6897
    },
    {
      "round": 113,
      "loss": 0.8855347454357452,
      "accuracy": 0.6937
    },
    {
      "round": 114,
      "loss": 0.8825644639353402,
      "accuracy": 0.6955
    },
    {
      "round": 115,
      "loss": 0.8791713149974141,
      "accuracy": 0.696
    },
    {
      "round": 116,
      "loss": 0.8746556722508452,
      "accuracy": 0.6962
    },
    {
      "round": 117,
      "loss": 0.8726907685732308,
      "accuracy": 0.6972
    },
    {
      "round": 118,
      "loss": 0.8669073315093312,
      "accuracy": 0.6988
    },
    {
      "round": 119,
      "loss": 0.8661563984883098,
      "accuracy": 0.6975
    },
    {
      "round": 120,
      "loss": 0.8591904698278957,
      "accuracy": 0.702
    },
    {
      "round": 121,
      "loss": 0.8575598425187242,
      "accuracy": 0.7008
    },
    {
      "round": 122,
      "loss": 0.8553260734286933,
      "accuracy": 0.7036
    },
    {
      "round": 123,
      "loss": 0.8501488621623371,
      "accuracy": 0.7068
    },
    {
      "round": 124,
      "loss": 0.8476834882752964,
      "accuracy": 0.7077
    },
    {
      "round": 125,
      "loss": 0.848530045142189,
      "accuracy": 0.7065
    },
    {
      "round": 126,
      "loss": 0.8429014299052973,
      "accuracy": 0.7088
    },
    {
      "round": 127,
      "loss": 0.8434888226346086,
      "accuracy": 0.7085
    },
    {
      "round": 128,
      "loss": 0.8380836690195833,
      "accuracy": 0.7097
    },
    {
      "round": 129,
      "loss": 0.8328180753004056,
      "accuracy": 0.7124
    },
    {
      "round": 130,
      "loss": 0.8343821723049822,
      "accuracy": 0.7101
    },
    {
      "round": 131,
      "loss": 0.8282908730613537,
      "accuracy": 0.7127
    },
    {
      "round": 132,
      "loss": 0.8280328301766429,
      "accuracy": 0.7132
    },
    {
      "round": 133,
      "loss": 0.82408865448385,
      "accuracy": 0.7158
    },
    {
      "round": 134,
      "loss": 0.8237220384061527,
      "accuracy": 0.7161
    },
    {
      "round": 135,
      "loss": 0.820449770925144,
      "accuracy": 0.7163
    },
    {
      "round": 136,
      "loss": 0.8227563196668228,
      "accuracy": 0.7181
    },
    {
      "round": 137,
      "loss": 0.8187672055948275,
      "accuracy": 0.7162
    },
    {
      "round": 138,
      "loss": 0.812696194972474,
      "accuracy": 0.7194
    },
    {
      "round": 139,
      "loss": 0.8144076161872084,
      "accuracy": 0.7173
    },
    {
      "round": 140,
      "loss": 0.810196405401626,
      "accuracy": 0.7197
    },
    {
      "round": 141,
      "loss": 0.8098146437456052,
      "accuracy": 0.7219
    },
    {
      "round": 142,
      "loss": 0.8122741201053412,
      "accuracy": 0.7207
    },
    {
      "round": 143,
      "loss": 0.8100949804813337,
      "accuracy": 0.7237
    },
    {
      "round": 144,
      "loss": 0.8045549573608861,
      "accuracy": 0.7249
    },
    {
      "round": 145,
      "loss": 0.8025244681979902,
      "accuracy": 0.726
    },
    {
      "round": 146,
      "loss": 0.8004497626719003,
      "accuracy": 0.7269
    },
    {
      "round": 147,
      "loss": 0.7935917542194025,
      "accuracy": 0.7302
    },
    {
      "round": 148,
      "loss": 0.7975585771064027,
      "accuracy": 0.7294
    },
    {
      "round": 149,
      "loss": 0.794476568603668,
      "accuracy": 0.73
    },
    {
      "round": 150,
      "loss": 0.7918115055408722,
      "accuracy": 0.7305
    },
    {
      "round": 151,
      "loss": 0.788328726546833,
      "accuracy": 0.7306
    },
    {
      "round": 152,
      "loss": 0.7880482666979963,
      "accuracy": 0.734
    },
    {
      "round": 153,
      "loss": 0.7869836008205963,
      "accuracy": 0.7309
    },
    {
      "round": 154,
      "loss": 0.7847162692691572,
      "accuracy": 0.7339
    },
    {
      "round": 155,
      "loss": 0.7824166947469925,
      "accuracy": 0.736
    },
    {
      "round": 156,
      "loss": 0.782739735449465,
      "accuracy": 0.7338
    },
    {
      "round": 157,
      "loss": 0.7845263373547088,
      "accuracy": 0.7328
    },
    {
      "round": 158,
      "loss": 0.7830470999399313,
      "accuracy": 0.7336
    },
    {
      "round": 159,
      "loss": 0.7814743694025107,
      "accuracy": 0.7372
    },
    {
      "round": 160,
      "loss": 0.7779019550203135,
      "accuracy": 0.7359
    },
    {
      "round": 161,
      "loss": 0.781000491529227,
      "accuracy": 0.7343
    },
    {
      "round": 162,
      "loss": 0.7802307760944001,
      "accuracy": 0.7366
    },
    {
      "round": 163,
      "loss": 0.7808476763601881,
      "accuracy": 0.7362
    },
    {
      "round": 164,
      "loss": 0.7769757897709124,
      "accuracy": 0.7391
    },
    {
      "round": 165,
      "loss": 0.7776522545007091,
      "accuracy": 0.7392
    },
    {
      "round": 166,
      "loss": 0.7759055218186242,
      "accuracy": 0.7396
    },
    {
      "round": 167,
      "loss": 0.7774442639023351,
      "accuracy": 0.7399
    },
    {
      "round": 168,
      "loss": 0.7763214043725413,
      "accuracy": 0.7403
    },
    {
      "round": 169,
      "loss": 0.7746981677536766,
      "accuracy": 0.7409
    },
    {
      "round": 170,
      "loss": 0.7697249102516296,
      "accuracy": 0.7411
    },
    {
      "round": 171,
      "loss": 0.7726060803325031,
      "accuracy": 0.7389
    },
    {
      "round": 172,
      "loss": 0.7702026693299174,
      "accuracy": 0.7391
    },
    {
      "round": 173,
      "loss": 0.7716596334125287,
      "accuracy": 0.7427
    },
    {
      "round": 174,
      "loss": 0.7746074976631627,
      "accuracy": 0.7438
    },
    {
      "round": 175,
      "loss": 0.7663792711667741,
      "accuracy": 0.7428
    },
    {
      "round": 176,
      "loss": 0.7695867406864898,
      "accuracy": 0.7441
    },
    {
      "round": 177,
      "loss": 0.7737792170466706,
      "accuracy": 0.7466
    },
    {
      "round": 178,
      "loss": 0.7722570384843662,
      "accuracy": 0.7441
    },
    {
      "round": 179,
      "loss": 0.7698964290915967,
      "accuracy": 0.7449
    },
    {
      "round": 180,
      "loss": 0.766613946936001,
      "accuracy": 0.7444
    },
    {
      "round": 181,
      "loss": 0.7715302090675306,
      "accuracy": 0.7487
    },
    {
      "round": 182,
      "loss": 0.7717969810810333,
      "accuracy": 0.7465
    },
    {
      "round": 183,
      "loss": 0.7683911973866411,
      "accuracy": 0.7461
    },
    {
      "round": 184,
      "loss": 0.7701260867876748,
      "accuracy": 0.746
    },
    {
      "round": 185,
      "loss": 0.7711413273700891,
      "accuracy": 0.7475
    },
    {
      "round": 186,
      "loss": 0.7677813929776414,
      "accuracy": 0.7475
    },
    {
      "round": 187,
      "loss": 0.7723733301932058,
      "accuracy": 0.7481
    },
    {
      "round": 188,
      "loss": 0.7743928530536139,
      "accuracy": 0.7479
    },
    {
      "round": 189,
      "loss": 0.7732559741019441,
      "accuracy": 0.7481
    },
    {
      "round": 190,
      "loss": 0.7757404120490193,
      "accuracy": 0.7493
    },
    {
      "round": 191,
      "loss": 0.773596290391855,
      "accuracy": 0.7507
    },
    {
      "round": 192,
      "loss": 0.7783262677276477,
      "accuracy": 0.7484
    },
    {
      "round": 193,
      "loss": 0.7730814026662717,
      "accuracy": 0.7487
    },
    {
      "round": 194,
      "loss": 0.7760756676570295,
      "accuracy": 0.7494
    },
    {
      "round": 195,
      "loss": 0.7734535523116017,
      "accuracy": 0.7503
    },
    {
      "round": 196,
      "loss": 0.7771836899149532,
      "accuracy": 0.7501
    },
    {
      "round": 197,
      "loss": 0.7790869149251487,
      "accuracy": 0.7503
    },
    {
      "round": 198,
      "loss": 0.7776011242843665,
      "accuracy": 0.7493
    },
    {
      "round": 199,
      "loss": 0.7762990838136917,
      "accuracy": 0.7512
    },
    {
      "round": 200,
      "loss": 0.7757570515520656,
      "accuracy": 0.7513
    },
    {
      "round": 201,
      "loss": 0.784210816644632,
      "accuracy": 0.7496
    },
    {
      "round": 202,
      "loss": 0.7803566824323453,
      "accuracy": 0.7506
    },
    {
      "round": 203,
      "loss": 0.786593990870558,
      "accuracy": 0.7508
    },
    {
      "round": 204,
      "loss": 0.7887046893183797,
      "accuracy": 0.7518
    },
    {
      "round": 205,
      "loss": 0.7821108988298776,
      "accuracy": 0.7514
    },
    {
      "round": 206,
      "loss": 0.7869353709986415,
      "accuracy": 0.752
    },
    {
      "round": 207,
      "loss": 0.7905862314251665,
      "accuracy": 0.7504
    },
    {
      "round": 208,
      "loss": 0.7934574209177456,
      "accuracy": 0.751
    },
    {
      "round": 209,
      "loss": 0.7921219257215342,
      "accuracy": 0.752
    },
    {
      "round": 210,
      "loss": 0.7956116394684337,
      "accuracy": 0.753
    },
    {
      "round": 211,
      "loss": 0.7966311645393555,
      "accuracy": 0.7515
    },
    {
      "round": 212,
      "loss": 0.7975476124701789,
      "accuracy": 0.7509
    },
    {
      "round": 213,
      "loss": 0.804976517066788,
      "accuracy": 0.7513
    },
    {
      "round": 214,
      "loss": 0.8010864671522056,
      "accuracy": 0.7525
    },
    {
      "round": 215,
      "loss": 0.8042275715178956,
      "accuracy": 0.7528
    },
    {
      "round": 216,
      "loss": 0.7995625630068702,
      "accuracy": 0.7531
    },
    {
      "round": 217,
      "loss": 0.8073666540388101,
      "accuracy": 0.754
    },
    {
      "round": 218,
      "loss": 0.8081511383334669,
      "accuracy": 0.754
    },
    {
      "round": 219,
      "loss": 0.809658829729778,
      "accuracy": 0.7547
    },
    {
      "round": 220,
      "loss": 0.811483906576047,
      "accuracy": 0.7532
    },
    {
      "round": 221,
      "loss": 0.8077386743820514,
      "accuracy": 0.7554
    },
    {
      "round": 222,
      "loss": 0.8158618835881114,
      "accuracy": 0.7539
    },
    {
      "round": 223,
      "loss": 0.8127082332540244,
      "accuracy": 0.7554
    },
    {
      "round": 224,
      "loss": 0.8243502878342954,
      "accuracy": 0.7522
    },
    {
      "round": 225,
      "loss": 0.811342934926097,
      "accuracy": 0.7549
    },
    {
      "round": 226,
      "loss": 0.81776265533397,
      "accuracy": 0.7549
    },
    {
      "round": 227,
      "loss": 0.8175201339367479,
      "accuracy": 0.7555
    },
    {
      "round": 228,
      "loss": 0.8265861737937592,
      "accuracy": 0.7564
    },
    {
      "round": 229,
      "loss": 0.828018441986733,
      "accuracy": 0.7562
    },
    {
      "round": 230,
      "loss": 0.8258910145336827,
      "accuracy": 0.7535
    },
    {
      "round": 231,
      "loss": 0.8270140106495196,
      "accuracy": 0.755
    },
    {
      "round": 232,
      "loss": 0.8363581504494237,
      "accuracy": 0.7547
    },
    {
      "round": 233,
      "loss": 0.8374084766013935,
      "accuracy": 0.7558
    },
    {
      "round": 234,
      "loss": 0.8376368132833475,
      "accuracy": 0.7568
    },
    {
      "round": 235,
      "loss": 0.8470144533216001,
      "accuracy": 0.7543
    },
    {
      "round": 236,
      "loss": 0.8396799396783018,
      "accuracy": 0.7548
    },
    {
      "round": 237,
      "loss": 0.860984733357978,
      "accuracy": 0.7547
    },
    {
      "round": 238,
      "loss": 0.8434925313098743,
      "accuracy": 0.7556
    },
    {
      "round": 239,
      "loss": 0.8533415957666434,
      "accuracy": 0.7552
    },
    {
      "round": 240,
      "loss": 0.8479550583198809,
      "accuracy": 0.7541
    },
    {
      "round": 241,
      "loss": 0.8572427252896677,
      "accuracy": 0.7523
    },
    {
      "round": 242,
      "loss": 0.8675301425373212,
      "accuracy": 0.7558
    },
    {
      "round": 243,
      "loss": 0.8702617873208591,
      "accuracy": 0.7554
    },
    {
      "round": 244,
      "loss": 0.8659856198504329,
      "accuracy": 0.7547
    },
    {
      "round": 245,
      "loss": 0.8721128674075246,
      "accuracy": 0.7529
    },
    {
      "round": 246,
      "loss": 0.8621114252474361,
      "accuracy": 0.7545
    },
    {
      "round": 247,
      "loss": 0.8664789464527045,
      "accuracy": 0.7527
    },
    {
      "round": 248,
      "loss": 0.8811968032734844,
      "accuracy": 0.7542
    },
    {
      "round": 249,
      "loss": 0.8711115499369253,
      "accuracy": 0.7546
    },
    {
      "round": 250,
      "loss": 0.8764076381445692,
      "accuracy": 0.7548
    },
    {
      "round": 251,
      "loss": 0.88261486756535,
      "accuracy": 0.7547
    },
    {
      "round": 252,
      "loss": 0.8813442054647989,
      "accuracy": 0.756
    },
    {
      "round": 253,
      "loss": 0.9012491166020353,
      "accuracy": 0.7572
    },
    {
      "round": 254,
      "loss": 0.8851565012154868,
      "accuracy": 0.755
    },
    {
      "round": 255,
      "loss": 0.9057162944405985,
      "accuracy": 0.7548
    },
    {
      "round": 256,
      "loss": 0.9025965983303972,
      "accuracy": 0.7546
    },
    {
      "round": 257,
      "loss": 0.9025693879531215,
      "accuracy": 0.7526
    },
    {
      "round": 258,
      "loss": 0.9098755186453414,
      "accuracy": 0.7547
    },
    {
      "round": 259,
      "loss": 0.9076089182505592,
      "accuracy": 0.7548
    },
    {
      "round": 260,
      "loss": 0.9105749092162988,
      "accuracy": 0.7532
    },
    {
      "round": 261,
      "loss": 0.9074399400347719,
      "accuracy": 0.7563
    },
    {
      "round": 262,
      "loss": 0.918263944621665,
      "accuracy": 0.7549
    },
    {
      "round": 263,
      "loss": 0.9170301276654862,
      "accuracy": 0.7551
    },
    {
      "round": 264,
      "loss": 0.8995571571131484,
      "accuracy": 0.7547
    },
    {
      "round": 265,
      "loss": 0.9298804223823091,
      "accuracy": 0.7546
    },
    {
      "round": 266,
      "loss": 0.9250256583427849,
      "accuracy": 0.7546
    },
    {
      "round": 267,
      "loss": 0.9307940864144042,
      "accuracy": 0.7555
    },
    {
      "round": 268,
      "loss": 0.93219158462823,
      "accuracy": 0.7552
    },
    {
      "round": 269,
      "loss": 0.9282669193161943,
      "accuracy": 0.7549
    },
    {
      "round": 270,
      "loss": 0.9273822988850621,
      "accuracy": 0.753
    },
    {
      "round": 271,
      "loss": 0.9352070082205172,
      "accuracy": 0.7531
    },
    {
      "round": 272,
      "loss": 0.9531501757736784,
      "accuracy": 0.7559
    },
    {
      "round": 273,
      "loss": 0.9587906720920112,
      "accuracy": 0.7538
    },
    {
      "round": 274,
      "loss": 0.9561481932862498,
      "accuracy": 0.7529
    },
    {
      "round": 275,
      "loss": 0.956588913790715,
      "accuracy": 0.7551
    },
    {
      "round": 276,
      "loss": 0.9602137367470196,
      "accuracy": 0.7538
    },
    {
      "round": 277,
      "loss": 0.9448215372074907,
      "accuracy": 0.7547
    },
    {
      "round": 278,
      "loss": 0.9615566959491553,
      "accuracy": 0.7546
    },
    {
      "round": 279,
      "loss": 0.9568266269688408,
      "accuracy": 0.7528
    },
    {
      "round": 280,
      "loss": 0.9806446728710169,
      "accuracy": 0.7555
    },
    {
      "round": 281,
      "loss": 0.9747413071675803,
      "accuracy": 0.7536
    },
    {
      "round": 282,
      "loss": 0.9940898809760523,
      "accuracy": 0.7532
    },
    {
      "round": 283,
      "loss": 0.9682257371588637,
      "accuracy": 0.7526
    },
    {
      "round": 284,
      "loss": 0.9869554094708385,
      "accuracy": 0.7543
    },
    {
      "round": 285,
      "loss": 0.974735328421806,
      "accuracy": 0.7541
    },
    {
      "round": 286,
      "loss": 0.992872919708776,
      "accuracy": 0.7538
    },
    {
      "round": 287,
      "loss": 0.9945296628977924,
      "accuracy": 0.7536
    },
    {
      "round": 288,
      "loss": 0.9929812445808143,
      "accuracy": 0.7529
    },
    {
      "round": 289,
      "loss": 0.9946334945698516,
      "accuracy": 0.7542
    },
    {
      "round": 290,
      "loss": 1.0147015001303472,
      "accuracy": 0.7519
    },
    {
      "round": 291,
      "loss": 1.0065600291703836,
      "accuracy": 0.7518
    },
    {
      "round": 292,
      "loss": 1.0222753668174196,
      "accuracy": 0.7532
    },
    {
      "round": 293,
      "loss": 1.0116881259714072,
      "accuracy": 0.7506
    },
    {
      "round": 294,
      "loss": 1.0055506226068107,
      "accuracy": 0.7544
    },
    {
      "round": 295,
      "loss": 1.0237875867385071,
      "accuracy": 0.7544
    },
    {
      "round": 296,
      "loss": 1.0361670961680884,
      "accuracy": 0.7545
    },
    {
      "round": 297,
      "loss": 1.0216618320241142,
      "accuracy": 0.7522
    },
    {
      "round": 298,
      "loss": 1.03169591910542,
      "accuracy": 0.7515
    },
    {
      "round": 299,
      "loss": 1.03680111686833,
      "accuracy": 0.7511
    },
    {
      "round": 300,
      "loss": 1.0486202997902332,
      "accuracy": 0.7547
    },
    {
      "round": 301,
      "loss": 1.0471589634308038,
      "accuracy": 0.7535
    },
    {
      "round": 302,
      "loss": 1.0234558082902774,
      "accuracy": 0.7526
    },
    {
      "round": 303,
      "loss": 1.0680108922548568,
      "accuracy": 0.7559
    },
    {
      "round": 304,
      "loss": 1.0508734231558852,
      "accuracy": 0.752
    },
    {
      "round": 305,
      "loss": 1.0495825470826876,
      "accuracy": 0.752
    },
    {
      "round": 306,
      "loss": 1.0547722452840866,
      "accuracy": 0.7546
    },
    {
      "round": 307,
      "loss": 1.059589272870804,
      "accuracy": 0.7525
    },
    {
      "round": 308,
      "loss": 1.064668857584746,
      "accuracy": 0.7572
    },
    {
      "round": 309,
      "loss": 1.0677691123451287,
      "accuracy": 0.7509
    },
    {
      "round": 310,
      "loss": 1.0596947400524213,
      "accuracy": 0.7536
    },
    {
      "round": 311,
      "loss": 1.091349782939917,
      "accuracy": 0.7505
    },
    {
      "round": 312,
      "loss": 1.0623994424415473,
      "accuracy": 0.7545
    },
    {
      "round": 313,
      "loss": 1.1128345174244798,
      "accuracy": 0.7532
    },
    {
      "round": 314,
      "loss": 1.0825916496328651,
      "accuracy": 0.7527
    },
    {
      "round": 315,
      "loss": 1.0841540969884433,
      "accuracy": 0.7539
    },
    {
      "round": 316,
      "loss": 1.0897276541485954,
      "accuracy": 0.7559
    },
    {
      "round": 317,
      "loss": 1.109898222854343,
      "accuracy": 0.7523
    },
    {
      "round": 318,
      "loss": 1.1134520245436281,
      "accuracy": 0.7529
    },
    {
      "round": 319,
      "loss": 1.0963003012699821,
      "accuracy": 0.7531
    },
    {
      "round": 320,
      "loss": 1.1144394869335925,
      "accuracy": 0.7524
    },
    {
      "round": 321,
      "loss": 1.09488785562043,
      "accuracy": 0.754
    },
    {
      "round": 322,
      "loss": 1.1114338818735208,
      "accuracy": 0.7544
    },
    {
      "round": 323,
      "loss": 1.1260438909926735,
      "accuracy": 0.7542
    },
    {
      "round": 324,
      "loss": 1.130174770951271,
      "accuracy": 0.7492
    },
    {
      "round": 325,
      "loss": 1.1080634236907045,
      "accuracy": 0.7529
    },
    {
      "round": 326,
      "loss": 1.1380800117319003,
      "accuracy": 0.7522
    },
    {
      "round": 327,
      "loss": 1.1343168894798992,
      "accuracy": 0.7535
    },
    {
      "round": 328,
      "loss": 1.1331924518076375,
      "accuracy": 0.7512
    },
    {
      "round": 329,
      "loss": 1.1378716352267768,
      "accuracy": 0.7549
    },
    {
      "round": 330,
      "loss": 1.1256719930008197,
      "accuracy": 0.7538
    },
    {
      "round": 331,
      "loss": 1.1535879059816703,
      "accuracy": 0.7538
    },
    {
      "round": 332,
      "loss": 1.1521389028325248,
      "accuracy": 0.7513
    },
    {
      "round": 333,
      "loss": 1.1626351479048165,
      "accuracy": 0.7525
    },
    {
      "round": 334,
      "loss": 1.1301993263986545,
      "accuracy": 0.7544
    },
    {
      "round": 335,
      "loss": 1.153584141843616,
      "accuracy": 0.7549
    },
    {
      "round": 336,
      "loss": 1.1491339138140693,
      "accuracy": 0.7554
    },
    {
      "round": 337,
      "loss": 1.160221960121831,
      "accuracy": 0.7534
    },
    {
      "round": 338,
      "loss": 1.150992033437799,
      "accuracy": 0.7539
    },
    {
      "round": 339,
      "loss": 1.175763474866605,
      "accuracy": 0.7515
    },
    {
      "round": 340,
      "loss": 1.191277807417769,
      "accuracy": 0.7558
    },
    {
      "round": 341,
      "loss": 1.1810516940709501,
      "accuracy": 0.7545
    },
    {
      "round": 342,
      "loss": 1.2117425025747226,
      "accuracy": 0.7526
    },
    {
      "round": 343,
      "loss": 1.1674086790972245,
      "accuracy": 0.7541
    },
    {
      "round": 344,
      "loss": 1.1919610826447369,
      "accuracy": 0.7527
    },
    {
      "round": 345,
      "loss": 1.200967040543739,
      "accuracy": 0.7523
    },
    {
      "round": 346,
      "loss": 1.1871729382691674,
      "accuracy": 0.7497
    },
    {
      "round": 347,
      "loss": 1.1941806549271836,
      "accuracy": 0.7529
    },
    {
      "round": 348,
      "loss": 1.1985606858239006,
      "accuracy": 0.7515
    },
    {
      "round": 349,
      "loss": 1.1971297339795115,
      "accuracy": 0.7521
    },
    {
      "round": 350,
      "loss": 1.2208253349930334,
      "accuracy": 0.7538
    },
    {
      "round": 351,
      "loss": 1.2135499264009464,
      "accuracy": 0.7523
    },
    {
      "round": 352,
      "loss": 1.2077529444671666,
      "accuracy": 0.7531
    },
    {
      "round": 353,
      "loss": 1.2175494974699264,
      "accuracy": 0.7519
    },
    {
      "round": 354,
      "loss": 1.2194615264955802,
      "accuracy": 0.752
    },
    {
      "round": 355,
      "loss": 1.228754373261342,
      "accuracy": 0.7522
    },
    {
      "round": 356,
      "loss": 1.2142660889667445,
      "accuracy": 0.7514
    },
    {
      "round": 357,
      "loss": 1.2244520178332496,
      "accuracy": 0.7517
    },
    {
      "round": 358,
      "loss": 1.240016642946024,
      "accuracy": 0.7546
    },
    {
      "round": 359,
      "loss": 1.2161521250828387,
      "accuracy": 0.7522
    },
    {
      "round": 360,
      "loss": 1.223461110418597,
      "accuracy": 0.7519
    },
    {
      "round": 361,
      "loss": 1.2301218409222154,
      "accuracy": 0.7544
    },
    {
      "round": 362,
      "loss": 1.2472365436176904,
      "accuracy": 0.7539
    },
    {
      "round": 363,
      "loss": 1.2551250587732266,
      "accuracy": 0.7496
    },
    {
      "round": 364,
      "loss": 1.2396497241795634,
      "accuracy": 0.7508
    },
    {
      "round": 365,
      "loss": 1.2378601876977153,
      "accuracy": 0.7497
    },
    {
      "round": 366,
      "loss": 1.2589703341737724,
      "accuracy": 0.751
    },
    {
      "round": 367,
      "loss": 1.2676532027629999,
      "accuracy": 0.7529
    },
    {
      "round": 368,
      "loss": 1.2831966801763723,
      "accuracy": 0.7508
    },
    {
      "round": 369,
      "loss": 1.2570702807781415,
      "accuracy": 0.7515
    },
    {
      "round": 370,
      "loss": 1.284648377912494,
      "accuracy": 0.7519
    },
    {
      "round": 371,
      "loss": 1.290795828349674,
      "accuracy": 0.7518
    },
    {
      "round": 372,
      "loss": 1.247787379228269,
      "accuracy": 0.7492
    },
    {
      "round": 373,
      "loss": 1.2971126380534217,
      "accuracy": 0.7507
    },
    {
      "round": 374,
      "loss": 1.2774851318365468,
      "accuracy": 0.751
    },
    {
      "round": 375,
      "loss": 1.2805804011825555,
      "accuracy": 0.7526
    },
    {
      "round": 376,
      "loss": 1.2925378674992358,
      "accuracy": 0.7501
    },
    {
      "round": 377,
      "loss": 1.2796679996073055,
      "accuracy": 0.7525
    },
    {
      "round": 378,
      "loss": 1.2666582758910359,
      "accuracy": 0.7511
    },
    {
      "round": 379,
      "loss": 1.3203577929125807,
      "accuracy": 0.7527
    },
    {
      "round": 380,
      "loss": 1.293443068814354,
      "accuracy": 0.753
    },
    {
      "round": 381,
      "loss": 1.324326737429768,
      "accuracy": 0.7511
    },
    {
      "round": 382,
      "loss": 1.3061518210191696,
      "accuracy": 0.7524
    },
    {
      "round": 383,
      "loss": 1.3140158588036943,
      "accuracy": 0.7506
    },
    {
      "round": 384,
      "loss": 1.3087601830688909,
      "accuracy": 0.7519
    },
    {
      "round": 385,
      "loss": 1.3189342749385407,
      "accuracy": 0.7513
    },
    {
      "round": 386,
      "loss": 1.3084407643007394,
      "accuracy": 0.7538
    },
    {
      "round": 387,
      "loss": 1.3240654808930314,
      "accuracy": 0.7509
    },
    {
      "round": 388,
      "loss": 1.3075526806112296,
      "accuracy": 0.7516
    },
    {
      "round": 389,
      "loss": 1.3428780900689359,
      "accuracy": 0.7514
    },
    {
      "round": 390,
      "loss": 1.3353341009955817,
      "accuracy": 0.7529
    },
    {
      "round": 391,
      "loss": 1.3298470257951047,
      "accuracy": 0.7508
    },
    {
      "round": 392,
      "loss": 1.3660829951778388,
      "accuracy": 0.7522
    },
    {
      "round": 393,
      "loss": 1.3523064903177011,
      "accuracy": 0.7538
    },
    {
      "round": 394,
      "loss": 1.3332158806986703,
      "accuracy": 0.7517
    },
    {
      "round": 395,
      "loss": 1.3216340539459221,
      "accuracy": 0.752
    },
    {
      "round": 396,
      "loss": 1.318928189266223,
      "accuracy": 0.7533
    },
    {
      "round": 397,
      "loss": 1.3623210616385975,
      "accuracy": 0.7542
    },
    {
      "round": 398,
      "loss": 1.3537355694241417,
      "accuracy": 0.7546
    },
    {
      "round": 399,
      "loss": 1.3807694627263676,
      "accuracy": 0.754
    },
    {
      "round": 400,
      "loss": 1.3391611669867183,
      "accuracy": 0.7511
    },
    {
      "round": 401,
      "loss": 1.384724158448533,
      "accuracy": 0.7521
    },
    {
      "round": 402,
      "loss": 1.3747719351095133,
      "accuracy": 0.7527
    },
    {
      "round": 403,
      "loss": 1.3700482099296185,
      "accuracy": 0.7522
    },
    {
      "round": 404,
      "loss": 1.3824103170880875,
      "accuracy": 0.7517
    },
    {
      "round": 405,
      "loss": 1.3688139301328994,
      "accuracy": 0.754
    },
    {
      "round": 406,
      "loss": 1.34522546984898,
      "accuracy": 0.7501
    },
    {
      "round": 407,
      "loss": 1.3684660341031254,
      "accuracy": 0.7516
    },
    {
      "round": 408,
      "loss": 1.3652071179673313,
      "accuracy": 0.7507
    },
    {
      "round": 409,
      "loss": 1.4236383948939295,
      "accuracy": 0.7536
    },
    {
      "round": 410,
      "loss": 1.3744901295382375,
      "accuracy": 0.7525
    },
    {
      "round": 411,
      "loss": 1.4254489739101155,
      "accuracy": 0.7528
    },
    {
      "round": 412,
      "loss": 1.3803264846721777,
      "accuracy": 0.7528
    },
    {
      "round": 413,
      "loss": 1.4090475312913189,
      "accuracy": 0.7527
    },
    {
      "round": 414,
      "loss": 1.38649929164888,
      "accuracy": 0.7538
    },
    {
      "round": 415,
      "loss": 1.3964075139060188,
      "accuracy": 0.7513
    },
    {
      "round": 416,
      "loss": 1.3767675104708716,
      "accuracy": 0.7521
    },
    {
      "round": 417,
      "loss": 1.3948425593467566,
      "accuracy": 0.7525
    },
    {
      "round": 418,
      "loss": 1.3868443749773616,
      "accuracy": 0.7533
    },
    {
      "round": 419,
      "loss": 1.3879235592989114,
      "accuracy": 0.7502
    },
    {
      "round": 420,
      "loss": 1.3828599054021196,
      "accuracy": 0.7536
    },
    {
      "round": 421,
      "loss": 1.4108428174314407,
      "accuracy": 0.7535
    },
    {
      "round": 422,
      "loss": 1.3977528766702159,
      "accuracy": 0.7522
    },
    {
      "round": 423,
      "loss": 1.398938209722979,
      "accuracy": 0.7523
    },
    {
      "round": 424,
      "loss": 1.4252206488920096,
      "accuracy": 0.7517
    },
    {
      "round": 425,
      "loss": 1.4413346898155852,
      "accuracy": 0.7528
    },
    {
      "round": 426,
      "loss": 1.4688078103164515,
      "accuracy": 0.7535
    },
    {
      "round": 427,
      "loss": 1.4060396598265195,
      "accuracy": 0.7524
    },
    {
      "round": 428,
      "loss": 1.4442211330508272,
      "accuracy": 0.7526
    },
    {
      "round": 429,
      "loss": 1.4262809423021614,
      "accuracy": 0.7514
    },
    {
      "round": 430,
      "loss": 1.4294630903691148,
      "accuracy": 0.7533
    },
    {
      "round": 431,
      "loss": 1.4235489514117805,
      "accuracy": 0.7533
    },
    {
      "round": 432,
      "loss": 1.4258226045309164,
      "accuracy": 0.7541
    },
    {
      "round": 433,
      "loss": 1.4380610118182704,
      "accuracy": 0.753
    },
    {
      "round": 434,
      "loss": 1.4522299617528915,
      "accuracy": 0.7517
    },
    {
      "round": 435,
      "loss": 1.4687741879647531,
      "accuracy": 0.7524
    },
    {
      "round": 436,
      "loss": 1.4671226440908047,
      "accuracy": 0.751
    },
    {
      "round": 437,
      "loss": 1.46232670816941,
      "accuracy": 0.7514
    },
    {
      "round": 438,
      "loss": 1.4679531081796835,
      "accuracy": 0.7525
    },
    {
      "round": 439,
      "loss": 1.4526439153919586,
      "accuracy": 0.7507
    },
    {
      "round": 440,
      "loss": 1.4317824026456656,
      "accuracy": 0.7537
    },
    {
      "round": 441,
      "loss": 1.4119976556148772,
      "accuracy": 0.7524
    },
    {
      "round": 442,
      "loss": 1.4508777363612628,
      "accuracy": 0.7515
    },
    {
      "round": 443,
      "loss": 1.458966399534061,
      "accuracy": 0.7534
    },
    {
      "round": 444,
      "loss": 1.4773912623572274,
      "accuracy": 0.753
    },
    {
      "round": 445,
      "loss": 1.4748617674405582,
      "accuracy": 0.7526
    },
    {
      "round": 446,
      "loss": 1.4408166397589084,
      "accuracy": 0.7507
    },
    {
      "round": 447,
      "loss": 1.443437697788397,
      "accuracy": 0.7506
    },
    {
      "round": 448,
      "loss": 1.4840251640104258,
      "accuracy": 0.7511
    },
    {
      "round": 449,
      "loss": 1.4247721824021384,
      "accuracy": 0.75
    },
    {
      "round": 450,
      "loss": 1.4689412037499796,
      "accuracy": 0.7516
    },
    {
      "round": 451,
      "loss": 1.47583749123846,
      "accuracy": 0.7507
    },
    {
      "round": 452,
      "loss": 1.4995565976197727,
      "accuracy": 0.7515
    },
    {
      "round": 453,
      "loss": 1.4475940520675799,
      "accuracy": 0.7508
    },
    {
      "round": 454,
      "loss": 1.4724803894948655,
      "accuracy": 0.7511
    },
    {
      "round": 455,
      "loss": 1.4688987460570595,
      "accuracy": 0.7527
    },
    {
      "round": 456,
      "loss": 1.4954821031790573,
      "accuracy": 0.7508
    },
    {
      "round": 457,
      "loss": 1.4789911487136786,
      "accuracy": 0.7514
    },
    {
      "round": 458,
      "loss": 1.4958014135924391,
      "accuracy": 0.7534
    },
    {
      "round": 459,
      "loss": 1.4938748273700952,
      "accuracy": 0.7514
    },
    {
      "round": 460,
      "loss": 1.505038610662515,
      "accuracy": 0.7534
    },
    {
      "round": 461,
      "loss": 1.5085292424256809,
      "accuracy": 0.7521
    },
    {
      "round": 462,
      "loss": 1.501375065110743,
      "accuracy": 0.7515
    },
    {
      "round": 463,
      "loss": 1.5098606763651576,
      "accuracy": 0.7498
    },
    {
      "round": 464,
      "loss": 1.4869257753459029,
      "accuracy": 0.7523
    },
    {
      "round": 465,
      "loss": 1.5184827840175872,
      "accuracy": 0.7527
    },
    {
      "round": 466,
      "loss": 1.4986824788415014,
      "accuracy": 0.7528
    },
    {
      "round": 467,
      "loss": 1.5180817398781212,
      "accuracy": 0.7548
    },
    {
      "round": 468,
      "loss": 1.5015959422142742,
      "accuracy": 0.7505
    },
    {
      "round": 469,
      "loss": 1.5356958291401117,
      "accuracy": 0.7533
    },
    {
      "round": 470,
      "loss": 1.5210109377345338,
      "accuracy": 0.7511
    },
    {
      "round": 471,
      "loss": 1.5283147696012886,
      "accuracy": 0.7524
    },
    {
      "round": 472,
      "loss": 1.526728798168155,
      "accuracy": 0.7518
    },
    {
      "round": 473,
      "loss": 1.5447577126681233,
      "accuracy": 0.7513
    },
    {
      "round": 474,
      "loss": 1.558776302126269,
      "accuracy": 0.7522
    },
    {
      "round": 475,
      "loss": 1.5408352115950263,
      "accuracy": 0.7506
    },
    {
      "round": 476,
      "loss": 1.5398654576878958,
      "accuracy": 0.7538
    },
    {
      "round": 477,
      "loss": 1.545623229191707,
      "accuracy": 0.7548
    },
    {
      "round": 478,
      "loss": 1.5564102460972418,
      "accuracy": 0.7531
    },
    {
      "round": 479,
      "loss": 1.525178358863337,
      "accuracy": 0.7528
    },
    {
      "round": 480,
      "loss": 1.5292344750782934,
      "accuracy": 0.7537
    },
    {
      "round": 481,
      "loss": 1.5493708540456363,
      "accuracy": 0.754
    },
    {
      "round": 482,
      "loss": 1.5587040548221753,
      "accuracy": 0.7533
    },
    {
      "round": 483,
      "loss": 1.5412363185764502,
      "accuracy": 0.7518
    },
    {
      "round": 484,
      "loss": 1.5501487139886179,
      "accuracy": 0.7538
    },
    {
      "round": 485,
      "loss": 1.541636844650625,
      "accuracy": 0.7518
    },
    {
      "round": 486,
      "loss": 1.5727466756162551,
      "accuracy": 0.7516
    },
    {
      "round": 487,
      "loss": 1.571996718930741,
      "accuracy": 0.7539
    },
    {
      "round": 488,
      "loss": 1.562920957089613,
      "accuracy": 0.7521
    },
    {
      "round": 489,
      "loss": 1.5774899760183816,
      "accuracy": 0.7517
    },
    {
      "round": 490,
      "loss": 1.548006544288355,
      "accuracy": 0.7521
    },
    {
      "round": 491,
      "loss": 1.5738842226445866,
      "accuracy": 0.7515
    },
    {
      "round": 492,
      "loss": 1.5506440648160422,
      "accuracy": 0.7525
    },
    {
      "round": 493,
      "loss": 1.573062539100647,
      "accuracy": 0.7539
    },
    {
      "round": 494,
      "loss": 1.566195843699641,
      "accuracy": 0.7535
    },
    {
      "round": 495,
      "loss": 1.5515919224903607,
      "accuracy": 0.7534
    },
    {
      "round": 496,
      "loss": 1.559100728160657,
      "accuracy": 0.7522
    },
    {
      "round": 497,
      "loss": 1.5692060746895238,
      "accuracy": 0.7538
    },
    {
      "round": 498,
      "loss": 1.5737717056426759,
      "accuracy": 0.7534
    },
    {
      "round": 499,
      "loss": 1.5471121715471006,
      "accuracy": 0.7513
    },
    {
      "round": 500,
      "loss": 1.5601490042841852,
      "accuracy": 0.7533
    }
  ],
  "config": {
    "dataset": "cifar10",
    "num_clients": 50,
    "malicious_ratio": 0.3,
    "strategy": "krum",
    "num_rounds": 500,
    "local_epochs": 1,
    "batch_size": 32,
    "learning_rate": 0.01,
    "iid": true,
    "filter_malicious": false,
    "trim_ratio": 0.1,
    "device": "cpu"
  }
}